Metadata-Version: 1.1
Name: require.py
Version: 2.0.1
Summary: Path-based imports in Python, inspired by `require.js`
Home-page: https://github.com/pcattori/require.py
Author: Pedro Cattori
Author-email: pcattori@gmail.com
License: MIT
Platform: UNKNOWN
Classifier: Development Status :: 5 - Production/Stable
Classifier: Intended Audience :: Developers
Classifier: License :: OSI Approved :: MIT License
Classifier: Programming Language :: Python
Classifier: Programming Language :: Python :: 2.7
Classifier: Programming Language :: Python :: 3.5
